handsignverify/__init__.py
handsignverify/model.py
handwritten_signature_verification-0.0.4.dist-info/LICENSE
handwritten_signature_verification-0.0.4.dist-info/METADATA
handwritten_signature_verification-0.0.4.dist-info/WHEEL
handwritten_signature_verification-0.0.4.dist-info/top_level.txt
handwritten_signature_verification-0.0.4.dist-info/RECORD
